pulseapi/__init__.py
pulseapi/actions.py
pulseapi/constants.py
pulseapi/environment.py
pulseapi/robot.py
pulseapi/utils.py
pulse_api-1.8.4.dist-info/LICENSE
pulse_api-1.8.4.dist-info/METADATA
pulse_api-1.8.4.dist-info/WHEEL
pulse_api-1.8.4.dist-info/top_level.txt
pulse_api-1.8.4.dist-info/RECORD
