Metadata-Version: 2.1
Name: pulse-api
Version: 1.8.4
Summary: Python API for Pulse Robotic Arm with useful utilities
Home-page: https://rozum.com
Author: Rozum Robotics
Author-email: dev@rozum.com
License: Apache License 2.0
Platform: UNKNOWN
Classifier: License :: OSI Approved :: Apache Software License
Classifier: Development Status :: 5 - Production/Stable
Classifier: Programming Language :: Python
Classifier: Programming Language :: Python :: 3
Classifier: Programming Language :: Python :: Implementation :: CPython
